expo_notifications/__init__.py
expo_notifications/admin.py
expo_notifications/apps.py
expo_notifications/conf.py
expo_notifications/managers/__init__.py
expo_notifications/managers/device_manager.py
expo_notifications/managers/message_manager.py
expo_notifications/managers/ticket_manager.py
expo_notifications/migrations/0001_initial.py
expo_notifications/migrations/__init__.py
expo_notifications/models/__init__.py
expo_notifications/models/device.py
expo_notifications/models/message.py
expo_notifications/models/receipt.py
expo_notifications/models/ticket.py
expo_notifications/py.typed
expo_notifications/tasks/__init__.py
expo_notifications/tasks/check_receipts_task.py
expo_notifications/tasks/send_messages_task.py
expo_notifications/tasks/session.py
django_expo_notifications-0.7.0.dist-info/WHEEL
django_expo_notifications-0.7.0.dist-info/METADATA
django_expo_notifications-0.7.0.dist-info/RECORD
