Metadata-Version: 2.3
Name: django-expo-notifications
Version: 0.7.0
Summary: Send and keep track of Expo push notifications with Django and Celery
Author: Jonathan Ehwald
Author-email: Jonathan Ehwald <github@ehwald.info>
License: MIT
Classifier: Development Status :: 5 - Production/Stable
Classifier: Environment :: Web Environment
Classifier: Framework :: Django
Classifier: Framework :: Django :: 4.2
Classifier: Framework :: Django :: 5.1
Classifier: Framework :: Django :: 5.2
Classifier: Intended Audience :: Developers
Classifier: License :: OSI Approved :: MIT License
Classifier: Operating System :: OS Independent
Classifier: Programming Language :: Python
Classifier: Programming Language :: Python :: 3
Classifier: Programming Language :: Python :: 3 :: Only
Classifier: Programming Language :: Python :: 3.10
Classifier: Programming Language :: Python :: 3.11
Classifier: Programming Language :: Python :: 3.12
Classifier: Programming Language :: Python :: 3.13
Classifier: Programming Language :: Python :: 3.14
Classifier: Topic :: Internet :: WWW/HTTP
Classifier: Topic :: Internet :: WWW/HTTP :: Dynamic Content
Classifier: Topic :: Software Development :: Libraries
Classifier: Topic :: Software Development :: Libraries :: Python Modules
Classifier: Typing :: Typed
Requires-Dist: django>=4.2
Requires-Dist: celery>=5.4
Requires-Dist: django-admin-anchors>=4.2.0,<5.0.0
Requires-Dist: exponent-server-sdk>=2.1.0,<3.0.0
Requires-Python: >=3.10, <4.0
Project-URL: homepage, https://github.com/DoctorJohn/django-expo-notifications
Project-URL: repository, https://github.com/DoctorJohn/django-expo-notifications
Project-URL: documentation, https://github.com/DoctorJohn/django-expo-notifications
